pcgym/__init__.py
pcgym/evaluation_metrics.py
pcgym/integrator.py
pcgym/model_classes.py
pcgym/oracle.py
pcgym/pcgym.py
pcgym/policy_evaluation.py
pcgym-0.1.8.dist-info/LICENSE
pcgym-0.1.8.dist-info/METADATA
pcgym-0.1.8.dist-info/WHEEL
pcgym-0.1.8.dist-info/top_level.txt
pcgym-0.1.8.dist-info/RECORD
