Metadata-Version: 2.1
Name: pcgym
Version: 0.1.8
Summary: Reinforcement learning suite of process control problems.
Author-email: Max Bloor <max.bloor@gmail.com>
License: MIT License
Project-URL: Documentation, https://maximilianb2.github.io/pc-gym/
Project-URL: Repository, https://github.com/MaximilianB2/pc-gym
Keywords: reinforcement-learning,process-control,jax,casadi,control
Classifier: Development Status :: 3 - Alpha
Classifier: Intended Audience :: Developers
Classifier: Intended Audience :: Information Technology
Classifier: Intended Audience :: Science/Research
Classifier: License :: OSI Approved :: MIT License
Classifier: Natural Language :: English
Classifier: Programming Language :: Python :: 3
Classifier: Topic :: Scientific/Engineering :: Artificial Intelligence
Classifier: Topic :: Scientific/Engineering :: Information Analysis
Classifier: Topic :: Scientific/Engineering :: Mathematics
Requires-Python: ~=3.11
License-File: LICENSE
Requires-Dist: ruff
Requires-Dist: numpy
Requires-Dist: tqdm
Requires-Dist: cloudpickle
Requires-Dist: matplotlib
Requires-Dist: gymnasium
Requires-Dist: casadi
Requires-Dist: jax[cpu]
Requires-Dist: equinox
Requires-Dist: diffrax
Requires-Dist: do-mpc[full]
Provides-Extra: optional
Requires-Dist: jupyterlab; extra == "optional"
Requires-Dist: torch; extra == "optional"
Requires-Dist: stable-baselines3; extra == "optional"
Requires-Dist: mkdocs-material; extra == "optional"
